[{"url":"https://flickr.com/photos/95271088@N05/47646706822","title":"алло, это прачечная?","photoUrl":"https://flickr.com/photos/95271088@N05/47646706822","latitude":49.840595,"longitude":24.025951},{"url":"https://flickr.com/photos/95271088@N05/47646705962","title":"","photoUrl":"https://flickr.com/photos/95271088@N05/47646705962","latitude":49.854706,"longitude":24.032335},{"url":"https://flickr.com/photos/95271088@N05/32756597817","title":"","photoUrl":"https://flickr.com/photos/95271088@N05/32756597817","latitude":50.441723,"longitude":30.521317},{"url":"https://flickr.com/photos/95271088@N05/40733467303","title":"","photoUrl":"https://flickr.com/photos/95271088@N05/40733467303","latitude":50.449287,"longitude":30.50576},{"url":"https://flickr.com/photos/95271088@N05/47646704162","title":"","photoUrl":"https://flickr.com/photos/95271088@N05/47646704162","latitude":50.437225,"longitude":30.489452},{"url":"https://flickr.com/photos/95271088@N05/40733467153","title":"","photoUrl":"https://flickr.com/photos/95271088@N05/40733467153","latitude":50.43761,"longitude":30.48516},{"url":"https://flickr.com/photos/95271088@N05/47699854421","title":"near Rizhok peak","photoUrl":"https://flickr.com/photos/95271088@N05/47699854421","latitude":48.591537,"longitude":23.004425},{"url":"https://flickr.com/photos/95271088@N05/40733442633","title":"","photoUrl":"https://flickr.com/photos/95271088@N05/40733442633","latitude":48.58467,"longitude":22.99696},{"url":"https://flickr.com/photos/95271088@N05/40733442293","title":"old man from Zakarpattia","photoUrl":"https://flickr.com/photos/95271088@N05/40733442293","latitude":48.57138,"longitude":22.966682},{"url":"https://flickr.com/photos/95271088@N05/40733441943","title":"","photoUrl":"https://flickr.com/photos/95271088@N05/40733441943","latitude":48.551414,"longitude":22.98344},{"url":"https://flickr.com/photos/95271088@N05/40733441543","title":"","photoUrl":"https://flickr.com/photos/95271088@N05/40733441543","latitude":49.211624,"longitude":28.441854},{"url":"https://flickr.com/photos/95271088@N05/40733440953","title":"Southern Buh","photoUrl":"https://flickr.com/photos/95271088@N05/40733440953","latitude":49.208366,"longitude":28.444933},{"url":"https://flickr.com/photos/95271088@N05/40733440133","title":"","photoUrl":"https://flickr.com/photos/95271088@N05/40733440133","latitude":49.552696,"longitude":25.597952},{"url":"https://flickr.com/photos/95271088@N05/40733439453","title":"","photoUrl":"https://flickr.com/photos/95271088@N05/40733439453","latitude":49.552773,"longitude":25.564253},{"url":"https://flickr.com/photos/95271088@N05/32756575707","title":"Oleksandr, the Izh driver","photoUrl":"https://flickr.com/photos/95271088@N05/32756575707","latitude":49.683006,"longitude":25.109833},{"url":"https://flickr.com/photos/95271088@N05/32756574457","title":"on the way","photoUrl":"https://flickr.com/photos/95271088@N05/32756574457","latitude":49.774563,"longitude":24.418648},{"url":"https://flickr.com/photos/95271088@N05/32756572317","title":"from scratch","photoUrl":"https://flickr.com/photos/95271088@N05/32756572317","latitude":49.818077,"longitude":24.154493},{"url":"https://flickr.com/photos/95271088@N05/46763551575","title":"","photoUrl":"https://flickr.com/photos/95271088@N05/46763551575","latitude":46.06348,"longitude":30.454327},{"url":"https://flickr.com/photos/95271088@N05/33802072798","title":"","photoUrl":"https://flickr.com/photos/95271088@N05/33802072798","latitude":46.0665,"longitude":30.45805},{"url":"https://flickr.com/photos/95271088@N05/40713294193","title":"","photoUrl":"https://flickr.com/photos/95271088@N05/40713294193","latitude":46.06439,"longitude":30.455507},{"url":"https://flickr.com/photos/95271088@N05/46792553534","title":"Natali","photoUrl":"https://flickr.com/photos/95271088@N05/46792553534","latitude":49.819794,"longitude":24.036325},{"url":"https://flickr.com/photos/95271088@N05/32574000877","title":"Nata and Liuda","photoUrl":"https://flickr.com/photos/95271088@N05/32574000877","latitude":49.84054,"longitude":24.033827},{"url":"https://flickr.com/photos/95271088@N05/47463585022","title":"first take","photoUrl":"https://flickr.com/photos/95271088@N05/47463585022","latitude":45.9179,"longitude":30.287374},{"url":"https://flickr.com/photos/95271088@N05/33524135908","title":"","photoUrl":"https://flickr.com/photos/95271088@N05/33524135908","latitude":50.44921,"longitude":30.50561},{"url":"https://flickr.com/photos/95271088@N05/32458131217","title":"kyiv cycle track","photoUrl":"https://flickr.com/photos/95271088@N05/32458131217","latitude":50.44921,"longitude":30.50561},{"url":"https://flickr.com/photos/95271088@N05/47347226102","title":"","photoUrl":"https://flickr.com/photos/95271088@N05/47347226102","latitude":50.442104,"longitude":30.51105},{"url":"https://flickr.com/photos/95271088@N05/40434327363","title":"Natali in Sheva","photoUrl":"https://flickr.com/photos/95271088@N05/40434327363","latitude":50.442104,"longitude":30.51105},{"url":"https://flickr.com/photos/95271088@N05/47347196202","title":"zhmerynka","photoUrl":"https://flickr.com/photos/95271088@N05/47347196202","latitude":49.03563,"longitude":28.10895},{"url":"https://flickr.com/photos/95271088@N05/40351753103","title":"urban zatoka","photoUrl":"https://flickr.com/photos/95271088@N05/40351753103","latitude":46.06184,"longitude":30.451376},{"url":"https://flickr.com/photos/95271088@N05/46593489014","title":"calmness","photoUrl":"https://flickr.com/photos/95271088@N05/46593489014","latitude":49.64818,"longitude":25.26645},{"url":"https://flickr.com/photos/95271088@N05/46593486134","title":"looking for Pyrohova Str. 187","photoUrl":"https://flickr.com/photos/95271088@N05/46593486134","latitude":49.21419,"longitude":28.417316},{"url":"https://flickr.com/photos/95271088@N05/47181039691","title":"сбпч, львів [3]","photoUrl":"https://flickr.com/photos/95271088@N05/47181039691","latitude":49.851,"longitude":24.052355},{"url":"https://flickr.com/photos/95271088@N05/46266829415","title":"сбпч, львів [2]","photoUrl":"https://flickr.com/photos/95271088@N05/46266829415","latitude":49.851,"longitude":24.052355},{"url":"https://flickr.com/photos/95271088@N05/46266828495","title":"сбпч, львів [1]","photoUrl":"https://flickr.com/photos/95271088@N05/46266828495","latitude":49.851,"longitude":24.052355},{"url":"https://flickr.com/photos/95271088@N05/46266823495","title":"","photoUrl":"https://flickr.com/photos/95271088@N05/46266823495","latitude":46.477665,"longitude":30.75659},{"url":"https://flickr.com/photos/95271088@N05/46266823325","title":"","photoUrl":"https://flickr.com/photos/95271088@N05/46266823325","latitude":46.477665,"longitude":30.75659},{"url":"https://flickr.com/photos/95271088@N05/46266822775","title":"","photoUrl":"https://flickr.com/photos/95271088@N05/46266822775","latitude":46.477665,"longitude":30.75659},{"url":"https://flickr.com/photos/95271088@N05/46266822245","title":"","photoUrl":"https://flickr.com/photos/95271088@N05/46266822245","latitude":46.47824,"longitude":30.75719},{"url":"https://flickr.com/photos/95271088@N05/46266821845","title":"","photoUrl":"https://flickr.com/photos/95271088@N05/46266821845","latitude":46.47806,"longitude":30.765238},{"url":"https://flickr.com/photos/95271088@N05/46266820845","title":"imago","photoUrl":"https://flickr.com/photos/95271088@N05/46266820845","latitude":49.844463,"longitude":24.036938},{"url":"https://flickr.com/photos/95271088@N05/46266815385","title":"мар\u0027яна клочко","photoUrl":"https://flickr.com/photos/95271088@N05/46266815385","latitude":49.844463,"longitude":24.036938},{"url":"https://flickr.com/photos/95271088@N05/40216215393","title":"","photoUrl":"https://flickr.com/photos/95271088@N05/40216215393","latitude":49.85153,"longitude":24.024277},{"url":"https://flickr.com/photos/95271088@N05/47181003301","title":"","photoUrl":"https://flickr.com/photos/95271088@N05/47181003301","latitude":49.817986,"longitude":24.02402},{"url":"https://flickr.com/photos/95271088@N05/46206603404","title":"elections are coming","photoUrl":"https://flickr.com/photos/95271088@N05/46206603404","latitude":49.83267,"longitude":24.040436},{"url":"https://flickr.com/photos/95271088@N05/46017140435","title":"hi!","photoUrl":"https://flickr.com/photos/95271088@N05/46017140435","latitude":49.823574,"longitude":24.033312},{"url":"https://flickr.com/photos/95271088@N05/46878923072","title":"","photoUrl":"https://flickr.com/photos/95271088@N05/46878923072","latitude":49.820484,"longitude":24.032764},{"url":"https://flickr.com/photos/95271088@N05/32935021518","title":"hello kitty!","photoUrl":"https://flickr.com/photos/95271088@N05/32935021518","latitude":46.19479,"longitude":30.351854},{"url":"https://flickr.com/photos/95271088@N05/46075028494","title":"їє!","photoUrl":"https://flickr.com/photos/95271088@N05/46075028494","latitude":49.84582,"longitude":24.029139},{"url":"https://flickr.com/photos/95271088@N05/46800045941","title":"","photoUrl":"https://flickr.com/photos/95271088@N05/46800045941","latitude":49.8423,"longitude":24.030338},{"url":"https://flickr.com/photos/95271088@N05/46075026634","title":"","photoUrl":"https://flickr.com/photos/95271088@N05/46075026634","latitude":49.825573,"longitude":24.033516},{"url":"https://flickr.com/photos/95271088@N05/45884765765","title":"two random guys","photoUrl":"https://flickr.com/photos/95271088@N05/45884765765","latitude":49.828625,"longitude":24.033321},{"url":"https://flickr.com/photos/95271088@N05/45884765185","title":"","photoUrl":"https://flickr.com/photos/95271088@N05/45884765185","latitude":49.845108,"longitude":24.02108},{"url":"https://flickr.com/photos/95271088@N05/32923961808","title":"","photoUrl":"https://flickr.com/photos/95271088@N05/32923961808","latitude":46.19865,"longitude":30.349539},{"url":"https://flickr.com/photos/95271088@N05/31857981257","title":"","photoUrl":"https://flickr.com/photos/95271088@N05/31857981257","latitude":45.93666,"longitude":30.304647},{"url":"https://flickr.com/photos/95271088@N05/46074726014","title":"","photoUrl":"https://flickr.com/photos/95271088@N05/46074726014","latitude":45.93666,"longitude":30.304647},{"url":"https://flickr.com/photos/95271088@N05/46074724554","title":"","photoUrl":"https://flickr.com/photos/95271088@N05/46074724554","latitude":45.934723,"longitude":30.301163},{"url":"https://flickr.com/photos/95271088@N05/31857978397","title":"","photoUrl":"https://flickr.com/photos/95271088@N05/31857978397","latitude":45.935574,"longitude":30.29821},{"url":"https://flickr.com/photos/95271088@N05/31857962397","title":"in the jungle","photoUrl":"https://flickr.com/photos/95271088@N05/31857962397","latitude":49.83572,"longitude":24.022432},{"url":"https://flickr.com/photos/95271088@N05/44603110370","title":"meow","photoUrl":"https://flickr.com/photos/95271088@N05/44603110370","latitude":46.46672,"longitude":30.740067},{"url":"https://flickr.com/photos/95271088@N05/44603108310","title":"three little birds","photoUrl":"https://flickr.com/photos/95271088@N05/44603108310","latitude":49.831665,"longitude":24.034481},{"url":"https://flickr.com/photos/95271088@N05/45696859454","title":"mountains and three little birds","photoUrl":"https://flickr.com/photos/95271088@N05/45696859454","latitude":49.83477,"longitude":24.03285},{"url":"https://flickr.com/photos/95271088@N05/44603109550","title":"","photoUrl":"https://flickr.com/photos/95271088@N05/44603109550","latitude":49.847767,"longitude":24.02594},{"url":"https://flickr.com/photos/95271088@N05/45696862224","title":"came back to odesa","photoUrl":"https://flickr.com/photos/95271088@N05/45696862224","latitude":46.466816,"longitude":30.74025},{"url":"https://flickr.com/photos/95271088@N05/44603111470","title":"dakhabrakha","photoUrl":"https://flickr.com/photos/95271088@N05/44603111470","latitude":49.844315,"longitude":24.02755},{"url":"https://flickr.com/photos/95271088@N05/46029794191","title":"dakh daughters","photoUrl":"https://flickr.com/photos/95271088@N05/46029794191","latitude":49.223904,"longitude":28.42839},{"url":"https://flickr.com/photos/95271088@N05/46029790821","title":"","photoUrl":"https://flickr.com/photos/95271088@N05/46029790821","latitude":49.223755,"longitude":28.427048},{"url":"https://flickr.com/photos/95271088@N05/45979945762","title":"","photoUrl":"https://flickr.com/photos/95271088@N05/45979945762","latitude":49.223755,"longitude":28.427048},{"url":"https://flickr.com/photos/95271088@N05/32158920198","title":"","photoUrl":"https://flickr.com/photos/95271088@N05/32158920198","latitude":49.230083,"longitude":28.453646},{"url":"https://flickr.com/photos/95271088@N05/32158919258","title":"","photoUrl":"https://flickr.com/photos/95271088@N05/32158919258","latitude":49.23114,"longitude":28.461498},{"url":"https://flickr.com/photos/95271088@N05/44214090880","title":"","photoUrl":"https://flickr.com/photos/95271088@N05/44214090880","latitude":49.23299,"longitude":28.468216},{"url":"https://flickr.com/photos/95271088@N05/45979926892","title":"gogol","photoUrl":"https://flickr.com/photos/95271088@N05/45979926892","latitude":49.223755,"longitude":28.427048},{"url":"https://flickr.com/photos/95271088@N05/45117778375","title":"","photoUrl":"https://flickr.com/photos/95271088@N05/45117778375","latitude":49.223747,"longitude":28.42752},{"url":"https://flickr.com/photos/95271088@N05/46029675271","title":"","photoUrl":"https://flickr.com/photos/95271088@N05/46029675271","latitude":49.841946,"longitude":24.034458},{"url":"https://flickr.com/photos/95271088@N05/46029657451","title":"","photoUrl":"https://flickr.com/photos/95271088@N05/46029657451","latitude":49.841118,"longitude":24.034567},{"url":"https://flickr.com/photos/95271088@N05/45117781765","title":"","photoUrl":"https://flickr.com/photos/95271088@N05/45117781765","latitude":49.84016,"longitude":24.034588},{"url":"https://flickr.com/photos/95271088@N05/44214097220","title":"","photoUrl":"https://flickr.com/photos/95271088@N05/44214097220","latitude":49.822105,"longitude":24.026798},{"url":"https://flickr.com/photos/95271088@N05/45140570214","title":"","photoUrl":"https://flickr.com/photos/95271088@N05/45140570214","latitude":49.829678,"longitude":24.03786},{"url":"https://flickr.com/photos/95271088@N05/44048431130","title":"","photoUrl":"https://flickr.com/photos/95271088@N05/44048431130","latitude":49.829678,"longitude":24.03786},{"url":"https://flickr.com/photos/95271088@N05/31993870188","title":"","photoUrl":"https://flickr.com/photos/95271088@N05/31993870188","latitude":49.8314,"longitude":24.039984},{"url":"https://flickr.com/photos/95271088@N05/44048414280","title":"","photoUrl":"https://flickr.com/photos/95271088@N05/44048414280","latitude":49.83878,"longitude":24.037355},{"url":"https://flickr.com/photos/95271088@N05/31899262698","title":"lviv modernism","photoUrl":"https://flickr.com/photos/95271088@N05/31899262698","latitude":49.81806,"longitude":24.033688},{"url":"https://flickr.com/photos/95271088@N05/30771438437","title":"","photoUrl":"https://flickr.com/photos/95271088@N05/30771438437","latitude":46.19727,"longitude":30.354527},{"url":"https://flickr.com/photos/95271088@N05/43880550780","title":"","photoUrl":"https://flickr.com/photos/95271088@N05/43880550780","latitude":49.84089,"longitude":24.030865},{"url":"https://flickr.com/photos/95271088@N05/45698545551","title":"","photoUrl":"https://flickr.com/photos/95271088@N05/45698545551","latitude":49.81665,"longitude":24.032549},{"url":"https://flickr.com/photos/95271088@N05/44969673934","title":"Liubko","photoUrl":"https://flickr.com/photos/95271088@N05/44969673934","latitude":42.40942,"longitude":27.70282},{"url":"https://flickr.com/photos/95271088@N05/45694407131","title":"modern and traditional","photoUrl":"https://flickr.com/photos/95271088@N05/45694407131","latitude":49.817917,"longitude":24.02211},{"url":"https://flickr.com/photos/95271088@N05/30716182627","title":"","photoUrl":"https://flickr.com/photos/95271088@N05/30716182627","latitude":49.88598,"longitude":24.00178},{"url":"https://flickr.com/photos/95271088@N05/31766420238","title":"","photoUrl":"https://flickr.com/photos/95271088@N05/31766420238","latitude":49.88598,"longitude":24.00178},{"url":"https://flickr.com/photos/95271088@N05/43820795740","title":"Sammy","photoUrl":"https://flickr.com/photos/95271088@N05/43820795740","latitude":49.88598,"longitude":24.00178},{"url":"https://flickr.com/photos/95271088@N05/45251606781","title":"","photoUrl":"https://flickr.com/photos/95271088@N05/45251606781","latitude":49.851585,"longitude":24.052462},{"url":"https://flickr.com/photos/95271088@N05/45251603931","title":"","photoUrl":"https://flickr.com/photos/95271088@N05/45251603931","latitude":45.935646,"longitude":30.301666},{"url":"https://flickr.com/photos/95271088@N05/45201062232","title":"ratusha is occupied!","photoUrl":"https://flickr.com/photos/95271088@N05/45201062232","latitude":49.841198,"longitude":24.030758},{"url":"https://flickr.com/photos/95271088@N05/45251226181","title":"O:","photoUrl":"https://flickr.com/photos/95271088@N05/45251226181","latitude":49.840992,"longitude":24.030329},{"url":"https://flickr.com/photos/95271088@N05/31377325518","title":"","photoUrl":"https://flickr.com/photos/95271088@N05/31377325518","latitude":49.841248,"longitude":24.029663},{"url":"https://flickr.com/photos/95271088@N05/30311903607","title":"","photoUrl":"https://flickr.com/photos/95271088@N05/30311903607","latitude":49.816174,"longitude":24.028654},{"url":"https://flickr.com/photos/95271088@N05/30311900727","title":"","photoUrl":"https://flickr.com/photos/95271088@N05/30311900727","latitude":49.81552,"longitude":24.032957},{"url":"https://flickr.com/photos/95271088@N05/44340093985","title":"","photoUrl":"https://flickr.com/photos/95271088@N05/44340093985","latitude":49.82026,"longitude":24.026863},{"url":"https://flickr.com/photos/95271088@N05/31377298648","title":"","photoUrl":"https://flickr.com/photos/95271088@N05/31377298648","latitude":49.81687,"longitude":24.035961},{"url":"https://flickr.com/photos/95271088@N05/31377288598","title":"","photoUrl":"https://flickr.com/photos/95271088@N05/31377288598","latitude":49.820736,"longitude":24.039738},{"url":"https://flickr.com/photos/95271088@N05/30311839247","title":"","photoUrl":"https://flickr.com/photos/95271088@N05/30311839247","latitude":42.414158,"longitude":27.700417},{"url":"https://flickr.com/photos/95271088@N05/44340033635","title":"","photoUrl":"https://flickr.com/photos/95271088@N05/44340033635","latitude":42.414158,"longitude":27.700417},{"url":"https://flickr.com/photos/95271088@N05/44340031195","title":"","photoUrl":"https://flickr.com/photos/95271088@N05/44340031195","latitude":42.414158,"longitude":27.700417},{"url":"https://flickr.com/photos/95271088@N05/44340029635","title":"a girl","photoUrl":"https://flickr.com/photos/95271088@N05/44340029635","latitude":42.414158,"longitude":27.700417},{"url":"https://flickr.com/photos/95271088@N05/44528688054","title":"nessebar","photoUrl":"https://flickr.com/photos/95271088@N05/44528688054","latitude":42.65978,"longitude":27.725887},{"url":"https://flickr.com/photos/95271088@N05/31377109568","title":"sammy","photoUrl":"https://flickr.com/photos/95271088@N05/31377109568","latitude":42.40942,"longitude":27.70282},{"url":"https://flickr.com/photos/95271088@N05/42465333990","title":"alicja w krainie czarów","photoUrl":"https://flickr.com/photos/95271088@N05/42465333990","latitude":45.933483,"longitude":30.30098},{"url":"https://flickr.com/photos/95271088@N05/44273197781","title":"09240001","photoUrl":"https://flickr.com/photos/95271088@N05/44273197781","latitude":49.83826,"longitude":24.033108},{"url":"https://flickr.com/photos/95271088@N05/43633785332","title":"","photoUrl":"https://flickr.com/photos/95271088@N05/43633785332","latitude":49.834957,"longitude":24.028023},{"url":"https://flickr.com/photos/95271088@N05/42777543125","title":"","photoUrl":"https://flickr.com/photos/95271088@N05/42777543125","latitude":49.833817,"longitude":24.027056},{"url":"https://flickr.com/photos/95271088@N05/41872250600","title":"","photoUrl":"https://flickr.com/photos/95271088@N05/41872250600","latitude":49.830654,"longitude":24.018517},{"url":"https://flickr.com/photos/95271088@N05/28791381247","title":"budaki lagoon","photoUrl":"https://flickr.com/photos/95271088@N05/28791381247","latitude":45.942257,"longitude":30.299648},{"url":"https://flickr.com/photos/95271088@N05/42777536155","title":"","photoUrl":"https://flickr.com/photos/95271088@N05/42777536155","latitude":45.942257,"longitude":30.296259},{"url":"https://flickr.com/photos/95271088@N05/42777536855","title":"","photoUrl":"https://flickr.com/photos/95271088@N05/42777536855","latitude":45.942257,"longitude":30.296259},{"url":"https://flickr.com/photos/95271088@N05/28791380087","title":"Fishka","photoUrl":"https://flickr.com/photos/95271088@N05/28791380087","latitude":45.942257,"longitude":30.296259},{"url":"https://flickr.com/photos/95271088@N05/43680477161","title":"","photoUrl":"https://flickr.com/photos/95271088@N05/43680477161","latitude":50.45919,"longitude":30.51783},{"url":"https://flickr.com/photos/95271088@N05/29415319818","title":"","photoUrl":"https://flickr.com/photos/95271088@N05/29415319818","latitude":50.447327,"longitude":30.546574},{"url":"https://flickr.com/photos/95271088@N05/29415318948","title":"","photoUrl":"https://flickr.com/photos/95271088@N05/29415318948","latitude":50.447327,"longitude":30.546574},{"url":"https://flickr.com/photos/95271088@N05/28415917207","title":"","photoUrl":"https://flickr.com/photos/95271088@N05/28415917207","latitude":50.447327,"longitude":30.546574},{"url":"https://flickr.com/photos/95271088@N05/43285042861","title":"","photoUrl":"https://flickr.com/photos/95271088@N05/43285042861","latitude":50.447327,"longitude":30.546574},{"url":"https://flickr.com/photos/95271088@N05/28415914267","title":"yo-yo!","photoUrl":"https://flickr.com/photos/95271088@N05/28415914267","latitude":50.447327,"longitude":30.546574},{"url":"https://flickr.com/photos/95271088@N05/43285039721","title":"white pouring —  29 hryvnias","photoUrl":"https://flickr.com/photos/95271088@N05/43285039721","latitude":50.445534,"longitude":30.521982},{"url":"https://flickr.com/photos/95271088@N05/43285041291","title":"crowd to an alcohol shop","photoUrl":"https://flickr.com/photos/95271088@N05/43285041291","latitude":50.445534,"longitude":30.521982},{"url":"https://flickr.com/photos/95271088@N05/43285040501","title":"","photoUrl":"https://flickr.com/photos/95271088@N05/43285040501","latitude":50.445534,"longitude":30.521982},{"url":"https://flickr.com/photos/95271088@N05/42566829234","title":"lviv opera","photoUrl":"https://flickr.com/photos/95271088@N05/42566829234","latitude":49.843094,"longitude":24.026884},{"url":"https://flickr.com/photos/95271088@N05/42677179451","title":"","photoUrl":"https://flickr.com/photos/95271088@N05/42677179451","latitude":49.827892,"longitude":24.005459},{"url":"https://flickr.com/photos/95271088@N05/28804497648","title":"","photoUrl":"https://flickr.com/photos/95271088@N05/28804497648","latitude":49.82871,"longitude":23.999107},{"url":"https://flickr.com/photos/95271088@N05/27809039607","title":"","photoUrl":"https://flickr.com/photos/95271088@N05/27809039607","latitude":49.823822,"longitude":23.989367},{"url":"https://flickr.com/photos/95271088@N05/27809038797","title":"","photoUrl":"https://flickr.com/photos/95271088@N05/27809038797","latitude":49.82049,"longitude":24.00032},{"url":"https://flickr.com/photos/95271088@N05/27809037757","title":"","photoUrl":"https://flickr.com/photos/95271088@N05/27809037757","latitude":49.815517,"longitude":24.004997},{"url":"https://flickr.com/photos/95271088@N05/41959637194","title":"Sheva boss","photoUrl":"https://flickr.com/photos/95271088@N05/41959637194","latitude":49.842716,"longitude":24.062462},{"url":"https://flickr.com/photos/95271088@N05/42628923762","title":"","photoUrl":"https://flickr.com/photos/95271088@N05/42628923762","latitude":49.829643,"longitude":24.037527},{"url":"https://flickr.com/photos/95271088@N05/42628922722","title":"","photoUrl":"https://flickr.com/photos/95271088@N05/42628922722","latitude":49.82511,"longitude":24.028},{"url":"https://flickr.com/photos/95271088@N05/42628922182","title":"","photoUrl":"https://flickr.com/photos/95271088@N05/42628922182","latitude":49.843185,"longitude":24.01859},{"url":"https://flickr.com/photos/95271088@N05/41778170765","title":"","photoUrl":"https://flickr.com/photos/95271088@N05/41778170765","latitude":49.836895,"longitude":24.019354},{"url":"https://flickr.com/photos/95271088@N05/42628921432","title":"the best biscuit ever","photoUrl":"https://flickr.com/photos/95271088@N05/42628921432","latitude":49.83556,"longitude":24.01915},{"url":"https://flickr.com/photos/95271088@N05/41778163935","title":"happiness","photoUrl":"https://flickr.com/photos/95271088@N05/41778163935","latitude":49.823364,"longitude":24.022078},{"url":"https://flickr.com/photos/95271088@N05/40347909300","title":"ghost","photoUrl":"https://flickr.com/photos/95271088@N05/40347909300","latitude":49.825962,"longitude":24.012358},{"url":"https://flickr.com/photos/95271088@N05/42154654091","title":"Lviv mountains","photoUrl":"https://flickr.com/photos/95271088@N05/42154654091","latitude":49.825962,"longitude":24.012358},{"url":"https://flickr.com/photos/95271088@N05/27988304668","title":"Tom, the cat","photoUrl":"https://flickr.com/photos/95271088@N05/27988304668","latitude":49.825962,"longitude":24.012358},{"url":"https://flickr.com/photos/95271088@N05/41856865151","title":"toy story","photoUrl":"https://flickr.com/photos/95271088@N05/41856865151","latitude":49.815384,"longitude":24.013699},{"url":"https://flickr.com/photos/95271088@N05/41856865601","title":":о","photoUrl":"https://flickr.com/photos/95271088@N05/41856865601","latitude":49.81756,"longitude":24.013},{"url":"https://flickr.com/photos/95271088@N05/41139714274","title":"","photoUrl":"https://flickr.com/photos/95271088@N05/41139714274","latitude":49.811527,"longitude":24.012497},{"url":"https://flickr.com/photos/95271088@N05/41139713334","title":"","photoUrl":"https://flickr.com/photos/95271088@N05/41139713334","latitude":50.418255,"longitude":30.466183},{"url":"https://flickr.com/photos/95271088@N05/41139711794","title":"drunk steps","photoUrl":"https://flickr.com/photos/95271088@N05/41139711794","latitude":49.818832,"longitude":24.01166},{"url":"https://flickr.com/photos/95271088@N05/41139710374","title":"","photoUrl":"https://flickr.com/photos/95271088@N05/41139710374","latitude":49.823505,"longitude":24.013742},{"url":"https://flickr.com/photos/95271088@N05/26988516287","title":"watchmaker\u0027s","photoUrl":"https://flickr.com/photos/95271088@N05/26988516287","latitude":49.836334,"longitude":24.020061},{"url":"https://flickr.com/photos/95271088@N05/41813913612","title":"O:","photoUrl":"https://flickr.com/photos/95271088@N05/41813913612","latitude":49.836258,"longitude":24.020458},{"url":"https://flickr.com/photos/95271088@N05/41813911752","title":"","photoUrl":"https://flickr.com/photos/95271088@N05/41813911752","latitude":49.821606,"longitude":24.037376},{"url":"https://flickr.com/photos/95271088@N05/41813936002","title":"castle on a hill","photoUrl":"https://flickr.com/photos/95271088@N05/41813936002","latitude":49.824272,"longitude":24.035748},{"url":"https://flickr.com/photos/95271088@N05/26988539787","title":"a bird","photoUrl":"https://flickr.com/photos/95271088@N05/26988539787","latitude":49.8209,"longitude":24.034801},{"url":"https://flickr.com/photos/95271088@N05/40467438054","title":"gang","photoUrl":"https://flickr.com/photos/95271088@N05/40467438054","latitude":49.825962,"longitude":24.012358},{"url":"https://flickr.com/photos/95271088@N05/27306446468","title":"calabash","photoUrl":"https://flickr.com/photos/95271088@N05/27306446468","latitude":49.825962,"longitude":24.012358},{"url":"https://flickr.com/photos/95271088@N05/40284365125","title":"yerba mate","photoUrl":"https://flickr.com/photos/95271088@N05/40284365125","latitude":49.825962,"longitude":24.012358},{"url":"https://flickr.com/photos/95271088@N05/39729754411","title":"","photoUrl":"https://flickr.com/photos/95271088@N05/39729754411","latitude":46.490482,"longitude":30.746042},{"url":"https://flickr.com/photos/95271088@N05/39729751001","title":"camel","photoUrl":"https://flickr.com/photos/95271088@N05/39729751001","latitude":46.490288,"longitude":30.745464},{"url":"https://flickr.com/photos/95271088@N05/39020523124","title":"","photoUrl":"https://flickr.com/photos/95271088@N05/39020523124","latitude":46.491146,"longitude":30.74673},{"url":"https://flickr.com/photos/95271088@N05/27950839499","title":"","photoUrl":"https://flickr.com/photos/95271088@N05/27950839499","latitude":49.825962,"longitude":24.012358},{"url":"https://flickr.com/photos/95271088@N05/39729735741","title":"","photoUrl":"https://flickr.com/photos/95271088@N05/39729735741","latitude":49.825962,"longitude":24.012358},{"url":"https://flickr.com/photos/95271088@N05/37109148283","title":"cloudy yogurt","photoUrl":"https://flickr.com/photos/95271088@N05/37109148283","latitude":49.825962,"longitude":24.012358},{"url":"https://flickr.com/photos/95271088@N05/37069967704","title":"alley","photoUrl":"https://flickr.com/photos/95271088@N05/37069967704","latitude":45.93492,"longitude":30.299456},{"url":"https://flickr.com/photos/95271088@N05/37730555616","title":"","photoUrl":"https://flickr.com/photos/95271088@N05/37730555616","latitude":45.934723,"longitude":30.301163},{"url":"https://flickr.com/photos/95271088@N05/37747305352","title":"","photoUrl":"https://flickr.com/photos/95271088@N05/37747305352","latitude":45.934723,"longitude":30.301163},{"url":"https://flickr.com/photos/95271088@N05/37778924551","title":"","photoUrl":"https://flickr.com/photos/95271088@N05/37778924551","latitude":45.934723,"longitude":30.301163},{"url":"https://flickr.com/photos/95271088@N05/37109145953","title":"sheptytsky","photoUrl":"https://flickr.com/photos/95271088@N05/37109145953","latitude":49.838627,"longitude":24.011316},{"url":"https://flickr.com/photos/95271088@N05/37778922131","title":"","photoUrl":"https://flickr.com/photos/95271088@N05/37778922131","latitude":49.825962,"longitude":24.012358},{"url":"https://flickr.com/photos/95271088@N05/37113762680","title":"home","photoUrl":"https://flickr.com/photos/95271088@N05/37113762680","latitude":52.298557,"longitude":13.009357},{"url":"https://flickr.com/photos/95271088@N05/37369958321","title":"good morning","photoUrl":"https://flickr.com/photos/95271088@N05/37369958321","latitude":52.298557,"longitude":13.009357},{"url":"https://flickr.com/photos/95271088@N05/36661301164","title":"liftplaats","photoUrl":"https://flickr.com/photos/95271088@N05/36661301164","latitude":52.348305,"longitude":4.920319},{"url":"https://flickr.com/photos/95271088@N05/36661299464","title":"","photoUrl":"https://flickr.com/photos/95271088@N05/36661299464","latitude":52.369938,"longitude":4.895439},{"url":"https://flickr.com/photos/95271088@N05/36661298554","title":"","photoUrl":"https://flickr.com/photos/95271088@N05/36661298554","latitude":52.39488,"longitude":4.891834},{"url":"https://flickr.com/photos/95271088@N05/37369955041","title":"","photoUrl":"https://flickr.com/photos/95271088@N05/37369955041","latitude":52.091637,"longitude":4.316082},{"url":"https://flickr.com/photos/95271088@N05/37369957471","title":"","photoUrl":"https://flickr.com/photos/95271088@N05/37369957471","latitude":52.079082,"longitude":4.340972},{"url":"https://flickr.com/photos/95271088@N05/37369949431","title":"","photoUrl":"https://flickr.com/photos/95271088@N05/37369949431","latitude":52.369938,"longitude":4.895439},{"url":"https://flickr.com/photos/95271088@N05/37369944041","title":"","photoUrl":"https://flickr.com/photos/95271088@N05/37369944041","latitude":52.369938,"longitude":4.895439},{"url":"https://flickr.com/photos/95271088@N05/37369942871","title":"","photoUrl":"https://flickr.com/photos/95271088@N05/37369942871","latitude":52.178143,"longitude":4.590911},{"url":"https://flickr.com/photos/95271088@N05/37369942661","title":"","photoUrl":"https://flickr.com/photos/95271088@N05/37369942661","latitude":52.091637,"longitude":4.316082},{"url":"https://flickr.com/photos/95271088@N05/37322743366","title":"port of rotterdam","photoUrl":"https://flickr.com/photos/95271088@N05/37322743366","latitude":52.104107,"longitude":4.256064},{"url":"https://flickr.com/photos/95271088@N05/36700087183","title":"","photoUrl":"https://flickr.com/photos/95271088@N05/36700087183","latitude":52.104107,"longitude":4.256064},{"url":"https://flickr.com/photos/95271088@N05/36700090143","title":"","photoUrl":"https://flickr.com/photos/95271088@N05/36700090143","latitude":52.109707,"longitude":4.273231},{"url":"https://flickr.com/photos/95271088@N05/37113733910","title":"","photoUrl":"https://flickr.com/photos/95271088@N05/37113733910","latitude":52.109707,"longitude":4.273231},{"url":"https://flickr.com/photos/95271088@N05/37113729940","title":"","photoUrl":"https://flickr.com/photos/95271088@N05/37113729940","latitude":52.113976,"longitude":4.279775},{"url":"https://flickr.com/photos/95271088@N05/37369937381","title":"","photoUrl":"https://flickr.com/photos/95271088@N05/37369937381","latitude":52.091637,"longitude":4.316082},{"url":"https://flickr.com/photos/95271088@N05/36700094113","title":"","photoUrl":"https://flickr.com/photos/95271088@N05/36700094113","latitude":52.09928,"longitude":4.291791},{"url":"https://flickr.com/photos/95271088@N05/37340143762","title":"","photoUrl":"https://flickr.com/photos/95271088@N05/37340143762","latitude":52.091637,"longitude":4.316082},{"url":"https://flickr.com/photos/95271088@N05/37340141202","title":"","photoUrl":"https://flickr.com/photos/95271088@N05/37340141202","latitude":52.091637,"longitude":4.316082},{"url":"https://flickr.com/photos/95271088@N05/37369925611","title":"hive","photoUrl":"https://flickr.com/photos/95271088@N05/37369925611","latitude":52.091637,"longitude":4.316082},{"url":"https://flickr.com/photos/95271088@N05/37369923701","title":"","photoUrl":"https://flickr.com/photos/95271088@N05/37369923701","latitude":52.0813,"longitude":4.32681},{"url":"https://flickr.com/photos/95271088@N05/37113710580","title":"","photoUrl":"https://flickr.com/photos/95271088@N05/37113710580","latitude":52.079876,"longitude":4.328355},{"url":"https://flickr.com/photos/95271088@N05/36699821853","title":"","photoUrl":"https://flickr.com/photos/95271088@N05/36699821853","latitude":52.393173,"longitude":4.848532},{"url":"https://flickr.com/photos/95271088@N05/36699823693","title":"поплавило","photoUrl":"https://flickr.com/photos/95271088@N05/36699823693","latitude":52.369938,"longitude":4.895439},{"url":"https://flickr.com/photos/95271088@N05/37369745621","title":"","photoUrl":"https://flickr.com/photos/95271088@N05/37369745621","latitude":52.369938,"longitude":4.895439},{"url":"https://flickr.com/photos/95271088@N05/37339951272","title":"","photoUrl":"https://flickr.com/photos/95271088@N05/37339951272","latitude":52.369938,"longitude":4.895439},{"url":"https://flickr.com/photos/95271088@N05/36661031504","title":"","photoUrl":"https://flickr.com/photos/95271088@N05/36661031504","latitude":52.38419,"longitude":4.842567},{"url":"https://flickr.com/photos/95271088@N05/23518056488","title":"","photoUrl":"https://flickr.com/photos/95271088@N05/23518056488","latitude":52.369938,"longitude":4.895439},{"url":"https://flickr.com/photos/95271088@N05/37339920532","title":"","photoUrl":"https://flickr.com/photos/95271088@N05/37339920532","latitude":52.11537,"longitude":4.28323},{"url":"https://flickr.com/photos/95271088@N05/23518054138","title":"","photoUrl":"https://flickr.com/photos/95271088@N05/23518054138","latitude":52.115623,"longitude":4.283884},{"url":"https://flickr.com/photos/95271088@N05/23518053408","title":"НЕМА","photoUrl":"https://flickr.com/photos/95271088@N05/23518053408","latitude":52.11465,"longitude":4.285558},{"url":"https://flickr.com/photos/95271088@N05/23518052998","title":"","photoUrl":"https://flickr.com/photos/95271088@N05/23518052998","latitude":51.152,"longitude":16.25822},{"url":"https://flickr.com/photos/95271088@N05/34608568832","title":"","photoUrl":"https://flickr.com/photos/95271088@N05/34608568832","latitude":50.445526,"longitude":30.50104},{"url":"https://flickr.com/photos/95271088@N05/34048042001","title":"","photoUrl":"https://flickr.com/photos/95271088@N05/34048042001","latitude":46.201347,"longitude":30.347391},{"url":"https://flickr.com/photos/95271088@N05/34048037441","title":"","photoUrl":"https://flickr.com/photos/95271088@N05/34048037441","latitude":46.19927,"longitude":30.345322},{"url":"https://flickr.com/photos/95271088@N05/34178982825","title":"","photoUrl":"https://flickr.com/photos/95271088@N05/34178982825","latitude":46.198917,"longitude":30.342081},{"url":"https://flickr.com/photos/95271088@N05/33978816905","title":"","photoUrl":"https://flickr.com/photos/95271088@N05/33978816905","latitude":49.835865,"longitude":24.02198},{"url":"https://flickr.com/photos/95271088@N05/33821174432","title":"","photoUrl":"https://flickr.com/photos/95271088@N05/33821174432","latitude":49.83522,"longitude":24.028837},{"url":"https://flickr.com/photos/95271088@N05/33848930291","title":"","photoUrl":"https://flickr.com/photos/95271088@N05/33848930291","latitude":49.832466,"longitude":24.0252},{"url":"https://flickr.com/photos/95271088@N05/33848929541","title":"","photoUrl":"https://flickr.com/photos/95271088@N05/33848929541","latitude":49.832466,"longitude":24.0252},{"url":"https://flickr.com/photos/95271088@N05/33978763715","title":"","photoUrl":"https://flickr.com/photos/95271088@N05/33978763715","latitude":49.832905,"longitude":24.023623},{"url":"https://flickr.com/photos/95271088@N05/33978660685","title":"","photoUrl":"https://flickr.com/photos/95271088@N05/33978660685","latitude":50.453964,"longitude":30.528881},{"url":"https://flickr.com/photos/95271088@N05/33593568440","title":"","photoUrl":"https://flickr.com/photos/95271088@N05/33593568440","latitude":49.83547,"longitude":24.010061},{"url":"https://flickr.com/photos/95271088@N05/33593564760","title":"весна політехніки","photoUrl":"https://flickr.com/photos/95271088@N05/33593564760","latitude":49.83549,"longitude":24.010115},{"url":"https://flickr.com/photos/95271088@N05/33135068104","title":"","photoUrl":"https://flickr.com/photos/95271088@N05/33135068104","latitude":49.825962,"longitude":24.012358},{"url":"https://flickr.com/photos/95271088@N05/33135063004","title":"","photoUrl":"https://flickr.com/photos/95271088@N05/33135063004","latitude":49.825962,"longitude":24.012358},{"url":"https://flickr.com/photos/95271088@N05/33041391521","title":"92480033","photoUrl":"https://flickr.com/photos/95271088@N05/33041391521","latitude":48.617134,"longitude":24.535025},{"url":"https://flickr.com/photos/95271088@N05/32786498570","title":"buzzy!","photoUrl":"https://flickr.com/photos/95271088@N05/32786498570","latitude":48.619392,"longitude":24.540539},{"url":"https://flickr.com/photos/95271088@N05/32353764273","title":"","photoUrl":"https://flickr.com/photos/95271088@N05/32353764273","latitude":48.58802,"longitude":24.537106},{"url":"https://flickr.com/photos/95271088@N05/32323788194","title":"92480023","photoUrl":"https://flickr.com/photos/95271088@N05/32323788194","latitude":48.583706,"longitude":24.53762},{"url":"https://flickr.com/photos/95271088@N05/32353726913","title":"","photoUrl":"https://flickr.com/photos/95271088@N05/32353726913","latitude":48.58473,"longitude":24.54217},{"url":"https://flickr.com/photos/95271088@N05/32353721613","title":"92480015","photoUrl":"https://flickr.com/photos/95271088@N05/32353721613","latitude":48.58802,"longitude":24.537106},{"url":"https://flickr.com/photos/95271088@N05/32353718063","title":"92480013","photoUrl":"https://flickr.com/photos/95271088@N05/32353718063","latitude":48.64601,"longitude":24.564548},{"url":"https://flickr.com/photos/95271088@N05/33041323721","title":"92480011","photoUrl":"https://flickr.com/photos/95271088@N05/33041323721","latitude":48.64408,"longitude":24.566051},{"url":"https://flickr.com/photos/95271088@N05/32323777864","title":"92480010","photoUrl":"https://flickr.com/photos/95271088@N05/32323777864","latitude":48.643642,"longitude":24.565622},{"url":"https://flickr.com/photos/95271088@N05/33168882605","title":"92480008","photoUrl":"https://flickr.com/photos/95271088@N05/33168882605","latitude":48.642223,"longitude":24.56487},{"url":"https://flickr.com/photos/95271088@N05/33168878115","title":"92480006","photoUrl":"https://flickr.com/photos/95271088@N05/33168878115","latitude":48.63588,"longitude":24.567072},{"url":"https://flickr.com/photos/95271088@N05/33127319536","title":"92480003","photoUrl":"https://flickr.com/photos/95271088@N05/33127319536","latitude":48.630028,"longitude":24.559464},{"url":"https://flickr.com/photos/95271088@N05/32323613294","title":"92520008","photoUrl":"https://flickr.com/photos/95271088@N05/32323613294","latitude":49.82604,"longitude":24.01224},{"url":"https://flickr.com/photos/95271088@N05/32323610384","title":"92520006","photoUrl":"https://flickr.com/photos/95271088@N05/32323610384","latitude":49.82604,"longitude":24.01224},{"url":"https://flickr.com/photos/95271088@N05/33168748555","title":"92520005","photoUrl":"https://flickr.com/photos/95271088@N05/33168748555","latitude":49.82604,"longitude":24.01224},{"url":"https://flickr.com/photos/95271088@N05/32353543133","title":"92520004","photoUrl":"https://flickr.com/photos/95271088@N05/32353543133","latitude":49.82604,"longitude":24.01224},{"url":"https://flickr.com/photos/95271088@N05/31831182053","title":"","photoUrl":"https://flickr.com/photos/95271088@N05/31831182053","latitude":46.203068,"longitude":30.350761},{"url":"https://flickr.com/photos/95271088@N05/32490106232","title":"nikitos","photoUrl":"https://flickr.com/photos/95271088@N05/32490106232","latitude":46.203068,"longitude":30.350761},{"url":"https://flickr.com/photos/95271088@N05/32643326805","title":"61510011","photoUrl":"https://flickr.com/photos/95271088@N05/32643326805","latitude":46.203068,"longitude":30.350761},{"url":"https://flickr.com/photos/95271088@N05/32643325505","title":"61510010","photoUrl":"https://flickr.com/photos/95271088@N05/32643325505","latitude":46.2003,"longitude":30.352434},{"url":"https://flickr.com/photos/95271088@N05/32520630331","title":"61510007","photoUrl":"https://flickr.com/photos/95271088@N05/32520630331","latitude":46.187317,"longitude":30.35914},{"url":"https://flickr.com/photos/95271088@N05/31701780832","title":"26940005","photoUrl":"https://flickr.com/photos/95271088@N05/31701780832","latitude":49.832943,"longitude":24.037947},{"url":"https://flickr.com/photos/95271088@N05/31701732362","title":"27000014","photoUrl":"https://flickr.com/photos/95271088@N05/31701732362","latitude":49.82604,"longitude":24.01224},{"url":"https://flickr.com/photos/95271088@N05/31039144783","title":"27000008","photoUrl":"https://flickr.com/photos/95271088@N05/31039144783","latitude":49.82604,"longitude":24.01224},{"url":"https://flickr.com/photos/95271088@N05/30710539994","title":"15510024","photoUrl":"https://flickr.com/photos/95271088@N05/30710539994","latitude":49.82601,"longitude":24.01226},{"url":"https://flickr.com/photos/95271088@N05/30710536854","title":"15510011","photoUrl":"https://flickr.com/photos/95271088@N05/30710536854","latitude":49.838993,"longitude":24.028032},{"url":"https://flickr.com/photos/95271088@N05/30710534834","title":"15510010","photoUrl":"https://flickr.com/photos/95271088@N05/30710534834","latitude":49.82601,"longitude":24.01226},{"url":"https://flickr.com/photos/95271088@N05/31551549715","title":"15510009","photoUrl":"https://flickr.com/photos/95271088@N05/31551549715","latitude":49.82601,"longitude":24.01226},{"url":"https://flickr.com/photos/95271088@N05/31435728891","title":"15510008","photoUrl":"https://flickr.com/photos/95271088@N05/31435728891","latitude":49.82601,"longitude":24.01226},{"url":"https://flickr.com/photos/95271088@N05/31435724811","title":"15500003","photoUrl":"https://flickr.com/photos/95271088@N05/31435724811","latitude":49.84016,"longitude":24.034588},{"url":"https://flickr.com/photos/95271088@N05/29470458323","title":"57980001","photoUrl":"https://flickr.com/photos/95271088@N05/29470458323","latitude":49.82547,"longitude":24.038858},{"url":"https://flickr.com/photos/95271088@N05/29983834392","title":"golden rain))0","photoUrl":"https://flickr.com/photos/95271088@N05/29983834392","latitude":49.82608,"longitude":24.012316},{"url":"https://flickr.com/photos/95271088@N05/30014683241","title":"57980010","photoUrl":"https://flickr.com/photos/95271088@N05/30014683241","latitude":49.88598,"longitude":24.00178},{"url":"https://flickr.com/photos/95271088@N05/29983760292","title":"57980012","photoUrl":"https://flickr.com/photos/95271088@N05/29983760292","latitude":49.88598,"longitude":24.00178},{"url":"https://flickr.com/photos/95271088@N05/30097812095","title":"57980009","photoUrl":"https://flickr.com/photos/95271088@N05/30097812095","latitude":49.88598,"longitude":24.00178},{"url":"https://flickr.com/photos/95271088@N05/29523512321","title":"AA034","photoUrl":"https://flickr.com/photos/95271088@N05/29523512321","latitude":48.37974,"longitude":24.488611},{"url":"https://flickr.com/photos/95271088@N05/29313899660","title":"AA032","photoUrl":"https://flickr.com/photos/95271088@N05/29313899660","latitude":48.371647,"longitude":24.489727},{"url":"https://flickr.com/photos/95271088@N05/29494335072","title":"carpathians \u003c3","photoUrl":"https://flickr.com/photos/95271088@N05/29494335072","latitude":48.371647,"longitude":24.489727},{"url":"https://flickr.com/photos/95271088@N05/29604247065","title":"AA023","photoUrl":"https://flickr.com/photos/95271088@N05/29604247065","latitude":48.371647,"longitude":24.489727},{"url":"https://flickr.com/photos/95271088@N05/29604245205","title":"good morning","photoUrl":"https://flickr.com/photos/95271088@N05/29604245205","latitude":48.37495,"longitude":24.495392},{"url":"https://flickr.com/photos/95271088@N05/28980575743","title":"AA017","photoUrl":"https://flickr.com/photos/95271088@N05/28980575743","latitude":48.370564,"longitude":24.494705},{"url":"https://flickr.com/photos/95271088@N05/28980570653","title":"AA015","photoUrl":"https://flickr.com/photos/95271088@N05/28980570653","latitude":48.35642,"longitude":24.506721},{"url":"https://flickr.com/photos/95271088@N05/28978777194","title":"AA016","photoUrl":"https://flickr.com/photos/95271088@N05/28978777194","latitude":48.36446,"longitude":24.508438},{"url":"https://flickr.com/photos/95271088@N05/29569920136","title":"AA012","photoUrl":"https://flickr.com/photos/95271088@N05/29569920136","latitude":48.36446,"longitude":24.508438},{"url":"https://flickr.com/photos/95271088@N05/28980504483","title":"AA009","photoUrl":"https://flickr.com/photos/95271088@N05/28980504483","latitude":48.35642,"longitude":24.506721},{"url":"https://flickr.com/photos/95271088@N05/29494274762","title":"AA007","photoUrl":"https://flickr.com/photos/95271088@N05/29494274762","latitude":48.354195,"longitude":24.505177},{"url":"https://flickr.com/photos/95271088@N05/29293062700","title":"AA035","photoUrl":"https://flickr.com/photos/95271088@N05/29293062700","latitude":49.837498,"longitude":24.02918},{"url":"https://flickr.com/photos/95271088@N05/29473342202","title":"AA024","photoUrl":"https://flickr.com/photos/95271088@N05/29473342202","latitude":46.200954,"longitude":30.347391},{"url":"https://flickr.com/photos/95271088@N05/29473321942","title":"AA017","photoUrl":"https://flickr.com/photos/95271088@N05/29473321942","latitude":59.937794,"longitude":30.303555},{"url":"https://flickr.com/photos/95271088@N05/29292959630","title":"AA010","photoUrl":"https://flickr.com/photos/95271088@N05/29292959630","latitude":55.11628,"longitude":30.321407},{"url":"https://flickr.com/photos/95271088@N05/29583215895","title":"AA021","photoUrl":"https://flickr.com/photos/95271088@N05/29583215895","latitude":52.425022,"longitude":31.013481},{"url":"https://flickr.com/photos/95271088@N05/28957461364","title":"AA018","photoUrl":"https://flickr.com/photos/95271088@N05/28957461364","latitude":52.4925,"longitude":31.959743},{"url":"https://flickr.com/photos/95271088@N05/28957451824","title":"somewhere in Polissya","photoUrl":"https://flickr.com/photos/95271088@N05/28957451824","latitude":51.97018,"longitude":31.72667},{"url":"https://flickr.com/photos/95271088@N05/29549028686","title":"AA010","photoUrl":"https://flickr.com/photos/95271088@N05/29549028686","latitude":46.199535,"longitude":30.355503},{"url":"https://flickr.com/photos/95271088@N05/28957388904","title":"AA007","photoUrl":"https://flickr.com/photos/95271088@N05/28957388904","latitude":45.463425,"longitude":29.484129},{"url":"https://flickr.com/photos/95271088@N05/29548971726","title":"AA005","photoUrl":"https://flickr.com/photos/95271088@N05/29548971726","latitude":45.45612,"longitude":29.485138},{"url":"https://flickr.com/photos/95271088@N05/29583051835","title":"AA003","photoUrl":"https://flickr.com/photos/95271088@N05/29583051835","latitude":45.45612,"longitude":29.485138},{"url":"https://flickr.com/photos/95271088@N05/28957292704","title":"AA025","photoUrl":"https://flickr.com/photos/95271088@N05/28957292704","latitude":45.45612,"longitude":29.485138},{"url":"https://flickr.com/photos/95271088@N05/29502427461","title":"AA024","photoUrl":"https://flickr.com/photos/95271088@N05/29502427461","latitude":45.47506,"longitude":29.42997},{"url":"https://flickr.com/photos/95271088@N05/29583009335","title":"AA016","photoUrl":"https://flickr.com/photos/95271088@N05/29583009335","latitude":45.930977,"longitude":30.29746},{"url":"https://flickr.com/photos/95271088@N05/29502335571","title":"пытля призадумался","photoUrl":"https://flickr.com/photos/95271088@N05/29502335571","latitude":46.200954,"longitude":30.347391},{"url":"https://flickr.com/photos/95271088@N05/29473001442","title":"колян звонит джулии","photoUrl":"https://flickr.com/photos/95271088@N05/29473001442","latitude":46.20257,"longitude":30.35162},{"url":"https://flickr.com/photos/95271088@N05/29472967692","title":"тёма тащит драм","photoUrl":"https://flickr.com/photos/95271088@N05/29472967692","latitude":46.20125,"longitude":30.35296},{"url":"https://flickr.com/photos/95271088@N05/28959344753","title":"AA022","photoUrl":"https://flickr.com/photos/95271088@N05/28959344753","latitude":46.197887,"longitude":30.358282},{"url":"https://flickr.com/photos/95271088@N05/29502231371","title":"AA012","photoUrl":"https://flickr.com/photos/95271088@N05/29502231371","latitude":46.44578,"longitude":30.771717},{"url":"https://flickr.com/photos/95271088@N05/28959231953","title":"AA020","photoUrl":"https://flickr.com/photos/95271088@N05/28959231953","latitude":46.202454,"longitude":30.35133},{"url":"https://flickr.com/photos/95271088@N05/29472836042","title":"AA019","photoUrl":"https://flickr.com/photos/95271088@N05/29472836042","latitude":46.193676,"longitude":30.346384},{"url":"https://flickr.com/photos/95271088@N05/29292498860","title":"AA008","photoUrl":"https://flickr.com/photos/95271088@N05/29292498860","latitude":45.94548,"longitude":30.305355},{"url":"https://flickr.com/photos/95271088@N05/28958410933","title":"Rita and Katya","photoUrl":"https://flickr.com/photos/95271088@N05/28958410933","latitude":46.199535,"longitude":30.355503},{"url":"https://flickr.com/photos/95271088@N05/29472015162","title":"little sister ^_^","photoUrl":"https://flickr.com/photos/95271088@N05/29472015162","latitude":46.190926,"longitude":30.351395},{"url":"https://flickr.com/photos/95271088@N05/29472013322","title":"AA021A","photoUrl":"https://flickr.com/photos/95271088@N05/29472013322","latitude":46.190926,"longitude":30.351395},{"url":"https://flickr.com/photos/95271088@N05/28956183844","title":"AA017A","photoUrl":"https://flickr.com/photos/95271088@N05/28956183844","latitude":46.194374,"longitude":30.34706},{"url":"https://flickr.com/photos/95271088@N05/29501348931","title":"AA014A","photoUrl":"https://flickr.com/photos/95271088@N05/29501348931","latitude":46.196926,"longitude":30.347553},{"url":"https://flickr.com/photos/95271088@N05/29501302801","title":"AA011A","photoUrl":"https://flickr.com/photos/95271088@N05/29501302801","latitude":46.196987,"longitude":30.349936},{"url":"https://flickr.com/photos/95271088@N05/29501250201","title":"AA022","photoUrl":"https://flickr.com/photos/95271088@N05/29501250201","latitude":46.12016,"longitude":30.34853},{"url":"https://flickr.com/photos/95271088@N05/29471766972","title":"AA019A","photoUrl":"https://flickr.com/photos/95271088@N05/29471766972","latitude":49.83908,"longitude":24.028278},{"url":"https://flickr.com/photos/95271088@N05/28958137293","title":"AA012A","photoUrl":"https://flickr.com/photos/95271088@N05/28958137293","latitude":49.82608,"longitude":24.012316},{"url":"https://flickr.com/photos/95271088@N05/29473231586","title":"44290005","photoUrl":"https://flickr.com/photos/95271088@N05/29473231586","latitude":49.55578,"longitude":25.589003},{"url":"https://flickr.com/photos/95271088@N05/28885084503","title":"43150008","photoUrl":"https://flickr.com/photos/95271088@N05/28885084503","latitude":46.19646,"longitude":30.327448},{"url":"https://flickr.com/photos/95271088@N05/29291305510","title":"44290021","photoUrl":"https://flickr.com/photos/95271088@N05/29291305510","latitude":49.83787,"longitude":24.025608},{"url":"https://flickr.com/photos/95271088@N05/29473116886","title":"43150019","photoUrl":"https://flickr.com/photos/95271088@N05/29473116886","latitude":49.82608,"longitude":24.012316},{"url":"https://flickr.com/photos/95271088@N05/29472769166","title":"29610021","photoUrl":"https://flickr.com/photos/95271088@N05/29472769166","latitude":49.831215,"longitude":24.034363},{"url":"https://flickr.com/photos/95271088@N05/26403128626","title":"27540001","photoUrl":"https://flickr.com/photos/95271088@N05/26403128626","latitude":49.830746,"longitude":24.038021},{"url":"https://flickr.com/photos/95271088@N05/25823236594","title":"капитошка :(","photoUrl":"https://flickr.com/photos/95271088@N05/25823236594","latitude":49.830307,"longitude":24.036432},{"url":"https://flickr.com/photos/95271088@N05/25825285043","title":"27540008","photoUrl":"https://flickr.com/photos/95271088@N05/25825285043","latitude":49.842335,"longitude":24.031347},{"url":"https://flickr.com/photos/95271088@N05/25825284063","title":"27540012","photoUrl":"https://flickr.com/photos/95271088@N05/25825284063","latitude":49.8421,"longitude":24.032303},{"url":"https://flickr.com/photos/95271088@N05/26335744482","title":"27540014","photoUrl":"https://flickr.com/photos/95271088@N05/26335744482","latitude":49.838966,"longitude":24.031649},{"url":"https://flickr.com/photos/95271088@N05/26155237390","title":"","photoUrl":"https://flickr.com/photos/95271088@N05/26155237390","latitude":49.838966,"longitude":24.031649},{"url":"https://flickr.com/photos/95271088@N05/26402144126","title":"27540016","photoUrl":"https://flickr.com/photos/95271088@N05/26402144126","latitude":49.83873,"longitude":24.031883},{"url":"https://flickr.com/photos/95271088@N05/26428082385","title":"27540017","photoUrl":"https://flickr.com/photos/95271088@N05/26428082385","latitude":49.835823,"longitude":24.026724},{"url":"https://flickr.com/photos/95271088@N05/25823228414","title":"27540018","photoUrl":"https://flickr.com/photos/95271088@N05/25823228414","latitude":49.835968,"longitude":24.025703},{"url":"https://flickr.com/photos/95271088@N05/26361888981","title":"27540028","photoUrl":"https://flickr.com/photos/95271088@N05/26361888981","latitude":49.828674,"longitude":24.021595},{"url":"https://flickr.com/photos/95271088@N05/26428062895","title":"27540029","photoUrl":"https://flickr.com/photos/95271088@N05/26428062895","latitude":49.82694,"longitude":24.019526},{"url":"https://flickr.com/photos/95271088@N05/26155113230","title":"dragon","photoUrl":"https://flickr.com/photos/95271088@N05/26155113230","latitude":49.82608,"longitude":24.012316},{"url":"https://flickr.com/photos/95271088@N05/26199976622","title":"23790003","photoUrl":"https://flickr.com/photos/95271088@N05/26199976622","latitude":49.845497,"longitude":24.030178},{"url":"https://flickr.com/photos/95271088@N05/26266448646","title":"little spider","photoUrl":"https://flickr.com/photos/95271088@N05/26266448646","latitude":49.849113,"longitude":23.996778},{"url":"https://flickr.com/photos/95271088@N05/26226130611","title":"23790009","photoUrl":"https://flickr.com/photos/95271088@N05/26226130611","latitude":49.851418,"longitude":23.99266},{"url":"https://flickr.com/photos/95271088@N05/26019533730","title":"","photoUrl":"https://flickr.com/photos/95271088@N05/26019533730","latitude":49.852345,"longitude":23.99813},{"url":"https://flickr.com/photos/95271088@N05/25687528204","title":"23790012","photoUrl":"https://flickr.com/photos/95271088@N05/25687528204","latitude":49.851185,"longitude":23.999546},{"url":"https://flickr.com/photos/95271088@N05/26019518030","title":"the xx","photoUrl":"https://flickr.com/photos/95271088@N05/26019518030","latitude":49.84997,"longitude":24.005856},{"url":"https://flickr.com/photos/95271088@N05/25687498774","title":"ігор біликівський","photoUrl":"https://flickr.com/photos/95271088@N05/25687498774","latitude":49.843227,"longitude":24.031776},{"url":"https://flickr.com/photos/95271088@N05/25113136312","title":"90890022","photoUrl":"https://flickr.com/photos/95271088@N05/25113136312","latitude":49.84124,"longitude":24.047249},{"url":"https://flickr.com/photos/95271088@N05/24604596163","title":"90890021","photoUrl":"https://flickr.com/photos/95271088@N05/24604596163","latitude":49.84124,"longitude":24.047249},{"url":"https://flickr.com/photos/95271088@N05/24595724733","title":"мрак","photoUrl":"https://flickr.com/photos/95271088@N05/24595724733","latitude":49.828335,"longitude":24.010073},{"url":"https://flickr.com/photos/95271088@N05/24522044464","title":"87180001","photoUrl":"https://flickr.com/photos/95271088@N05/24522044464","latitude":49.84116,"longitude":24.035017},{"url":"https://flickr.com/photos/95271088@N05/24785025529","title":"87180002","photoUrl":"https://flickr.com/photos/95271088@N05/24785025529","latitude":49.838577,"longitude":24.03198},{"url":"https://flickr.com/photos/95271088@N05/25034466082","title":"87180003","photoUrl":"https://flickr.com/photos/95271088@N05/25034466082","latitude":49.83954,"longitude":24.038376},{"url":"https://flickr.com/photos/95271088@N05/24525865533","title":"87180004","photoUrl":"https://flickr.com/photos/95271088@N05/24525865533","latitude":49.83938,"longitude":24.038462},{"url":"https://flickr.com/photos/95271088@N05/25152717395","title":"87180008","photoUrl":"https://flickr.com/photos/95271088@N05/25152717395","latitude":49.84016,"longitude":24.027197},{"url":"https://flickr.com/photos/95271088@N05/25034456402","title":"87180010","photoUrl":"https://flickr.com/photos/95271088@N05/25034456402","latitude":49.836952,"longitude":24.012133},{"url":"https://flickr.com/photos/95271088@N05/24522019084","title":"87180014","photoUrl":"https://flickr.com/photos/95271088@N05/24522019084","latitude":49.120792,"longitude":24.728765},{"url":"https://flickr.com/photos/95271088@N05/25059415421","title":"into dust","photoUrl":"https://flickr.com/photos/95271088@N05/25059415421","latitude":49.12071,"longitude":24.729494},{"url":"https://flickr.com/photos/95271088@N05/24857020810","title":"87180019","photoUrl":"https://flickr.com/photos/95271088@N05/24857020810","latitude":49.12161,"longitude":24.730225},{"url":"https://flickr.com/photos/95271088@N05/24996910632","title":"86460011","photoUrl":"https://flickr.com/photos/95271088@N05/24996910632","latitude":49.82608,"longitude":24.012316},{"url":"https://flickr.com/photos/95271088@N05/24746536719","title":"86460007","photoUrl":"https://flickr.com/photos/95271088@N05/24746536719","latitude":49.835304,"longitude":24.02137},{"url":"https://flickr.com/photos/95271088@N05/24976235232","title":"86460002","photoUrl":"https://flickr.com/photos/95271088@N05/24976235232","latitude":49.825974,"longitude":24.01225},{"url":"https://flickr.com/photos/95271088@N05/25007317235","title":"","photoUrl":"https://flickr.com/photos/95271088@N05/25007317235","latitude":49.825974,"longitude":24.01225},{"url":"https://flickr.com/photos/95271088@N05/25006262115","title":"AA028","photoUrl":"https://flickr.com/photos/95271088@N05/25006262115","latitude":49.842743,"longitude":24.030264},{"url":"https://flickr.com/photos/95271088@N05/24912976081","title":"AA027","photoUrl":"https://flickr.com/photos/95271088@N05/24912976081","latitude":49.841015,"longitude":24.030039},{"url":"https://flickr.com/photos/95271088@N05/24638624849","title":"AA023","photoUrl":"https://flickr.com/photos/95271088@N05/24638624849","latitude":49.826916,"longitude":24.013699},{"url":"https://flickr.com/photos/95271088@N05/24912954361","title":"AA013","photoUrl":"https://flickr.com/photos/95271088@N05/24912954361","latitude":46.193943,"longitude":30.347532},{"url":"https://flickr.com/photos/95271088@N05/24379420693","title":"AA014","photoUrl":"https://flickr.com/photos/95271088@N05/24379420693","latitude":46.19828,"longitude":30.35001},{"url":"https://flickr.com/photos/95271088@N05/24888213672","title":"AA009","photoUrl":"https://flickr.com/photos/95271088@N05/24888213672","latitude":46.19446,"longitude":30.343445},{"url":"https://flickr.com/photos/95271088@N05/24888194512","title":"AA033","photoUrl":"https://flickr.com/photos/95271088@N05/24888194512","latitude":46.193542,"longitude":30.345697},{"url":"https://flickr.com/photos/95271088@N05/24912928511","title":"AA031","photoUrl":"https://flickr.com/photos/95271088@N05/24912928511","latitude":46.19446,"longitude":30.343445},{"url":"https://flickr.com/photos/95271088@N05/25006210215","title":"AA026","photoUrl":"https://flickr.com/photos/95271088@N05/25006210215","latitude":46.194008,"longitude":30.347198},{"url":"https://flickr.com/photos/95271088@N05/24375610694","title":"AA024","photoUrl":"https://flickr.com/photos/95271088@N05/24375610694","latitude":46.19446,"longitude":30.343445},{"url":"https://flickr.com/photos/95271088@N05/24638583359","title":"AA019","photoUrl":"https://flickr.com/photos/95271088@N05/24638583359","latitude":45.463833,"longitude":29.484964},{"url":"https://flickr.com/photos/95271088@N05/24379350193","title":"AA013A","photoUrl":"https://flickr.com/photos/95271088@N05/24379350193","latitude":45.459873,"longitude":29.492153},{"url":"https://flickr.com/photos/95271088@N05/25006167325","title":"AA007A","photoUrl":"https://flickr.com/photos/95271088@N05/25006167325","latitude":45.45551,"longitude":29.495586},{"url":"https://flickr.com/photos/95271088@N05/24888142462","title":"AA001A","photoUrl":"https://flickr.com/photos/95271088@N05/24888142462","latitude":45.46153,"longitude":29.483679},{"url":"https://flickr.com/photos/95271088@N05/24888140762","title":"AA000A","photoUrl":"https://flickr.com/photos/95271088@N05/24888140762","latitude":45.46231,"longitude":29.483313},{"url":"https://flickr.com/photos/95271088@N05/24841623922","title":"AA024","photoUrl":"https://flickr.com/photos/95271088@N05/24841623922","latitude":46.197655,"longitude":30.358412},{"url":"https://flickr.com/photos/95271088@N05/24959580585","title":"AA023","photoUrl":"https://flickr.com/photos/95271088@N05/24959580585","latitude":46.197506,"longitude":30.359892},{"url":"https://flickr.com/photos/95271088@N05/24933284496","title":"AA017","photoUrl":"https://flickr.com/photos/95271088@N05/24933284496","latitude":46.19651,"longitude":30.360641},{"url":"https://flickr.com/photos/95271088@N05/24664084940","title":"AA015","photoUrl":"https://flickr.com/photos/95271088@N05/24664084940","latitude":46.19629,"longitude":30.36046},{"url":"https://flickr.com/photos/95271088@N05/24332734103","title":"AA010","photoUrl":"https://flickr.com/photos/95271088@N05/24332734103","latitude":46.194424,"longitude":30.356092},{"url":"https://flickr.com/photos/95271088@N05/24328979734","title":"AA009","photoUrl":"https://flickr.com/photos/95271088@N05/24328979734","latitude":46.19446,"longitude":30.343445},{"url":"https://flickr.com/photos/95271088@N05/24328977794","title":"AA008","photoUrl":"https://flickr.com/photos/95271088@N05/24328977794","latitude":46.195747,"longitude":30.348476},{"url":"https://flickr.com/photos/95271088@N05/24866245631","title":"AA005","photoUrl":"https://flickr.com/photos/95271088@N05/24866245631","latitude":46.196007,"longitude":30.352692},{"url":"https://flickr.com/photos/95271088@N05/24919677436","title":"AA019","photoUrl":"https://flickr.com/photos/95271088@N05/24919677436","latitude":46.202972,"longitude":30.350246},{"url":"https://flickr.com/photos/95271088@N05/24852641811","title":"AA021","photoUrl":"https://flickr.com/photos/95271088@N05/24852641811","latitude":46.202972,"longitude":30.350246},{"url":"https://flickr.com/photos/95271088@N05/24318744363","title":"84600026","photoUrl":"https://flickr.com/photos/95271088@N05/24318744363","latitude":49.90364,"longitude":23.9407},{"url":"https://flickr.com/photos/95271088@N05/24827668052","title":"84600025","photoUrl":"https://flickr.com/photos/95271088@N05/24827668052","latitude":49.903893,"longitude":23.938963},{"url":"https://flickr.com/photos/95271088@N05/24827671342","title":"AA029","photoUrl":"https://flickr.com/photos/95271088@N05/24827671342","latitude":49.83511,"longitude":24.010502},{"url":"https://flickr.com/photos/95271088@N05/24650142780","title":"AA013","photoUrl":"https://flickr.com/photos/95271088@N05/24650142780","latitude":49.82608,"longitude":24.012316},{"url":"https://flickr.com/photos/95271088@N05/46811048841","title":"bandera monument, ternopil","photoUrl":"https://flickr.com/photos/95271088@N05/46811048841","latitude":49.55566,"longitude":25.590677},{"url":"https://flickr.com/photos/95271088@N05/24327729804","title":"ternopil atmosphere","photoUrl":"https://flickr.com/photos/95271088@N05/24327729804","latitude":49.551804,"longitude":25.591944},{"url":"https://flickr.com/photos/95271088@N05/24590708709","title":"AA025","photoUrl":"https://flickr.com/photos/95271088@N05/24590708709","latitude":49.55225,"longitude":25.592072},{"url":"https://flickr.com/photos/95271088@N05/24485689729","title":"AA023","photoUrl":"https://flickr.com/photos/95271088@N05/24485689729","latitude":49.5529,"longitude":25.590977},{"url":"https://flickr.com/photos/95271088@N05/24485693789","title":"¯\\_(.___.)_/¯","photoUrl":"https://flickr.com/photos/95271088@N05/24485693789","latitude":49.553516,"longitude":25.588165},{"url":"https://flickr.com/photos/95271088@N05/24759835731","title":"AA021","photoUrl":"https://flickr.com/photos/95271088@N05/24759835731","latitude":49.554512,"longitude":25.587372},{"url":"https://flickr.com/photos/95271088@N05/24735425872","title":"AA013","photoUrl":"https://flickr.com/photos/95271088@N05/24735425872","latitude":49.555172,"longitude":25.59176},{"url":"https://flickr.com/photos/95271088@N05/24226407993","title":"AA006","photoUrl":"https://flickr.com/photos/95271088@N05/24226407993","latitude":49.553776,"longitude":25.594915},{"url":"https://flickr.com/photos/95271088@N05/32625942966","title":"16430020","photoUrl":"https://flickr.com/photos/95271088@N05/32625942966","latitude":49.835457,"longitude":24.010061},{"url":"https://flickr.com/photos/95271088@N05/22303302753","title":"16430024","photoUrl":"https://flickr.com/photos/95271088@N05/22303302753","latitude":49.837124,"longitude":24.01357},{"url":"https://flickr.com/photos/95271088@N05/24663282270","title":"AA007","photoUrl":"https://flickr.com/photos/95271088@N05/24663282270","latitude":49.840855,"longitude":24.034878},{"url":"https://flickr.com/photos/95271088@N05/24650148410","title":"AA008","photoUrl":"https://flickr.com/photos/95271088@N05/24650148410","latitude":49.84187,"longitude":24.034147},{"url":"https://flickr.com/photos/95271088@N05/22625679880","title":"11950003","photoUrl":"https://flickr.com/photos/95271088@N05/22625679880","latitude":49.837753,"longitude":24.018087},{"url":"https://flickr.com/photos/95271088@N05/22792120715","title":"11950004","photoUrl":"https://flickr.com/photos/95271088@N05/22792120715","latitude":49.82608,"longitude":24.012316},{"url":"https://flickr.com/photos/95271088@N05/22169332224","title":"11900002","photoUrl":"https://flickr.com/photos/95271088@N05/22169332224","latitude":50.439194,"longitude":30.520073},{"url":"https://flickr.com/photos/95271088@N05/22373691938","title":"","photoUrl":"https://flickr.com/photos/95271088@N05/22373691938","latitude":50.439194,"longitude":30.520073},{"url":"https://flickr.com/photos/95271088@N05/22373701337","title":"11900003","photoUrl":"https://flickr.com/photos/95271088@N05/22373701337","latitude":50.439194,"longitude":30.520073},{"url":"https://flickr.com/photos/95271088@N05/22416500357","title":"harbour bridge, kyiv","photoUrl":"https://flickr.com/photos/95271088@N05/22416500357","latitude":50.46376,"longitude":30.525963},{"url":"https://flickr.com/photos/95271088@N05/22373691617","title":"11900010","photoUrl":"https://flickr.com/photos/95271088@N05/22373691617","latitude":50.46376,"longitude":30.525963},{"url":"https://flickr.com/photos/95271088@N05/22213715053","title":"11900017","photoUrl":"https://flickr.com/photos/95271088@N05/22213715053","latitude":50.453266,"longitude":30.516039},{"url":"https://flickr.com/photos/95271088@N05/22766060396","title":"11900022","photoUrl":"https://flickr.com/photos/95271088@N05/22766060396","latitude":50.4482,"longitude":30.514225},{"url":"https://flickr.com/photos/95271088@N05/22766071506","title":"11900024","photoUrl":"https://flickr.com/photos/95271088@N05/22766071506","latitude":50.44624,"longitude":30.513763},{"url":"https://flickr.com/photos/95271088@N05/22420487980","title":"06500009","photoUrl":"https://flickr.com/photos/95271088@N05/22420487980","latitude":49.843754,"longitude":24.041454},{"url":"https://flickr.com/photos/95271088@N05/22564710856","title":"06500010","photoUrl":"https://flickr.com/photos/95271088@N05/22564710856","latitude":49.835144,"longitude":24.01076},{"url":"https://flickr.com/photos/95271088@N05/22601918871","title":"06500006","photoUrl":"https://flickr.com/photos/95271088@N05/22601918871","latitude":49.840042,"longitude":24.040789},{"url":"https://flickr.com/photos/95271088@N05/21969524753","title":"","photoUrl":"https://flickr.com/photos/95271088@N05/21969524753","latitude":49.84016,"longitude":24.042227},{"url":"https://flickr.com/photos/95271088@N05/22564707626","title":"06500004","photoUrl":"https://flickr.com/photos/95271088@N05/22564707626","latitude":49.841084,"longitude":24.046219},{"url":"https://flickr.com/photos/95271088@N05/21987413053","title":"94670001","photoUrl":"https://flickr.com/photos/95271088@N05/21987413053","latitude":49.842224,"longitude":24.030779},{"url":"https://flickr.com/photos/95271088@N05/22577101742","title":"94670007","photoUrl":"https://flickr.com/photos/95271088@N05/22577101742","latitude":49.841724,"longitude":24.032549},{"url":"https://flickr.com/photos/95271088@N05/21967882764","title":"94670008","photoUrl":"https://flickr.com/photos/95271088@N05/21967882764","latitude":49.841198,"longitude":24.030758},{"url":"https://flickr.com/photos/95271088@N05/22577095952","title":"94670010","photoUrl":"https://flickr.com/photos/95271088@N05/22577095952","latitude":49.841484,"longitude":24.026348},{"url":"https://flickr.com/photos/95271088@N05/21969451543","title":"94670011","photoUrl":"https://flickr.com/photos/95271088@N05/21969451543","latitude":49.84129,"longitude":24.026112},{"url":"https://flickr.com/photos/95271088@N05/22564633776","title":"94670013","photoUrl":"https://flickr.com/photos/95271088@N05/22564633776","latitude":49.84129,"longitude":24.026112},{"url":"https://flickr.com/photos/95271088@N05/22590637905","title":"94670016","photoUrl":"https://flickr.com/photos/95271088@N05/22590637905","latitude":49.84129,"longitude":24.026112},{"url":"https://flickr.com/photos/95271088@N05/22564629936","title":"94670015","photoUrl":"https://flickr.com/photos/95271088@N05/22564629936","latitude":49.84129,"longitude":24.026112},{"url":"https://flickr.com/photos/95271088@N05/22402667790","title":"94670019","photoUrl":"https://flickr.com/photos/95271088@N05/22402667790","latitude":49.838593,"longitude":24.022894},{"url":"https://flickr.com/photos/95271088@N05/22576895072","title":"62980025","photoUrl":"https://flickr.com/photos/95271088@N05/22576895072","latitude":46.20207,"longitude":30.34985},{"url":"https://flickr.com/photos/95271088@N05/22576893372","title":"62980023","photoUrl":"https://flickr.com/photos/95271088@N05/22576893372","latitude":46.201035,"longitude":30.352917},{"url":"https://flickr.com/photos/95271088@N05/22601639891","title":"62980021","photoUrl":"https://flickr.com/photos/95271088@N05/22601639891","latitude":46.20029,"longitude":30.35207},{"url":"https://flickr.com/photos/95271088@N05/22576886282","title":"62980020","photoUrl":"https://flickr.com/photos/95271088@N05/22576886282","latitude":46.20029,"longitude":30.35207},{"url":"https://flickr.com/photos/95271088@N05/22576885282","title":"62980018","photoUrl":"https://flickr.com/photos/95271088@N05/22576885282","latitude":46.194477,"longitude":30.355932},{"url":"https://flickr.com/photos/95271088@N05/21967673284","title":"grapes in every yard","photoUrl":"https://flickr.com/photos/95271088@N05/21967673284","latitude":46.193897,"longitude":30.352156},{"url":"https://flickr.com/photos/95271088@N05/22564429736","title":"62980016","photoUrl":"https://flickr.com/photos/95271088@N05/22564429736","latitude":46.194046,"longitude":30.352028},{"url":"https://flickr.com/photos/95271088@N05/22576888612","title":"akkerman letterboxes","photoUrl":"https://flickr.com/photos/95271088@N05/22576888612","latitude":46.194664,"longitude":30.353485},{"url":"https://flickr.com/photos/95271088@N05/21967669334","title":"62980012","photoUrl":"https://flickr.com/photos/95271088@N05/21967669334","latitude":46.195934,"longitude":30.357273},{"url":"https://flickr.com/photos/95271088@N05/22402465210","title":"62980009","photoUrl":"https://flickr.com/photos/95271088@N05/22402465210","latitude":46.196217,"longitude":30.355246},{"url":"https://flickr.com/photos/95271088@N05/22601514571","title":"62980006","photoUrl":"https://flickr.com/photos/95271088@N05/22601514571","latitude":46.19479,"longitude":30.352274},{"url":"https://flickr.com/photos/95271088@N05/22576764032","title":"cat","photoUrl":"https://flickr.com/photos/95271088@N05/22576764032","latitude":46.195644,"longitude":30.348154},{"url":"https://flickr.com/photos/95271088@N05/21969123923","title":"62980004","photoUrl":"https://flickr.com/photos/95271088@N05/21969123923","latitude":46.19589,"longitude":30.347586},{"url":"https://flickr.com/photos/95271088@N05/22576757152","title":"62980001","photoUrl":"https://flickr.com/photos/95271088@N05/22576757152","latitude":46.196957,"longitude":30.348143},{"url":"https://flickr.com/photos/95271088@N05/22582696316","title":"AA010","photoUrl":"https://flickr.com/photos/95271088@N05/22582696316","latitude":46.457417,"longitude":30.76718},{"url":"https://flickr.com/photos/95271088@N05/22577052462","title":"AA007","photoUrl":"https://flickr.com/photos/95271088@N05/22577052462","latitude":46.457417,"longitude":30.76718},{"url":"https://flickr.com/photos/95271088@N05/22576987252","title":"AA006","photoUrl":"https://flickr.com/photos/95271088@N05/22576987252","latitude":46.457417,"longitude":30.76718},{"url":"https://flickr.com/photos/95271088@N05/21967834394","title":"AA009","photoUrl":"https://flickr.com/photos/95271088@N05/21967834394","latitude":46.457417,"longitude":30.76718},{"url":"https://flickr.com/photos/95271088@N05/21967761114","title":"AA015","photoUrl":"https://flickr.com/photos/95271088@N05/21967761114","latitude":46.48407,"longitude":30.738855},{"url":"https://flickr.com/photos/95271088@N05/22420856850","title":"истории о маленьком кролике","photoUrl":"https://flickr.com/photos/95271088@N05/22420856850","latitude":46.4852,"longitude":30.73407},{"url":"https://flickr.com/photos/95271088@N05/22601723561","title":"AA012","photoUrl":"https://flickr.com/photos/95271088@N05/22601723561","latitude":46.483826,"longitude":30.734747},{"url":"https://flickr.com/photos/95271088@N05/21986004604","title":"AA005","photoUrl":"https://flickr.com/photos/95271088@N05/21986004604","latitude":46.49012,"longitude":30.738447},{"url":"https://flickr.com/photos/95271088@N05/22402547180","title":"AA004","photoUrl":"https://flickr.com/photos/95271088@N05/22402547180","latitude":46.488186,"longitude":30.741194},{"url":"https://flickr.com/photos/95271088@N05/22601711731","title":"AA002","photoUrl":"https://flickr.com/photos/95271088@N05/22601711731","latitude":46.190178,"longitude":30.35061},{"url":"https://flickr.com/photos/95271088@N05/22576631452","title":"24A","photoUrl":"https://flickr.com/photos/95271088@N05/22576631452","latitude":46.202007,"longitude":30.349463},{"url":"https://flickr.com/photos/95271088@N05/22402133800","title":"23A","photoUrl":"https://flickr.com/photos/95271088@N05/22402133800","latitude":49.82106,"longitude":24.048504},{"url":"https://flickr.com/photos/95271088@N05/22564091996","title":"mystery","photoUrl":"https://flickr.com/photos/95271088@N05/22564091996","latitude":49.84213,"longitude":24.036015},{"url":"https://flickr.com/photos/95271088@N05/22576540522","title":"12A","photoUrl":"https://flickr.com/photos/95271088@N05/22576540522","latitude":49.842506,"longitude":24.036606},{"url":"https://flickr.com/photos/95271088@N05/21969471123","title":"99910002","photoUrl":"https://flickr.com/photos/95271088@N05/21969471123","latitude":49.825974,"longitude":24.01225},{"url":"https://flickr.com/photos/95271088@N05/21969475003","title":"99910009","photoUrl":"https://flickr.com/photos/95271088@N05/21969475003","latitude":49.841843,"longitude":24.031433},{"url":"https://flickr.com/photos/95271088@N05/22590669195","title":"99910012","photoUrl":"https://flickr.com/photos/95271088@N05/22590669195","latitude":49.842964,"longitude":24.029997},{"url":"https://flickr.com/photos/95271088@N05/21967914194","title":"99910023","photoUrl":"https://flickr.com/photos/95271088@N05/21967914194","latitude":49.82831,"longitude":24.058212},{"url":"https://flickr.com/photos/95271088@N05/22577134712","title":"99910024","photoUrl":"https://flickr.com/photos/95271088@N05/22577134712","latitude":49.828182,"longitude":24.05831},{"url":"https://flickr.com/photos/95271088@N05/21985833064","title":"000008","photoUrl":"https://flickr.com/photos/95271088@N05/21985833064","latitude":49.828564,"longitude":24.01283},{"url":"https://flickr.com/photos/95271088@N05/21987462713","title":"000013","photoUrl":"https://flickr.com/photos/95271088@N05/21987462713","latitude":49.828564,"longitude":24.01283},{"url":"https://flickr.com/photos/95271088@N05/22563995106","title":"000020","photoUrl":"https://flickr.com/photos/95271088@N05/22563995106","latitude":49.124386,"longitude":24.72147},{"url":"https://flickr.com/photos/95271088@N05/22576447272","title":"000021","photoUrl":"https://flickr.com/photos/95271088@N05/22576447272","latitude":49.124332,"longitude":24.726963},{"url":"https://flickr.com/photos/95271088@N05/22619834211","title":"000026","photoUrl":"https://flickr.com/photos/95271088@N05/22619834211","latitude":49.835457,"longitude":24.010061},{"url":"https://flickr.com/photos/95271088@N05/22601219141","title":"colour Lviv","photoUrl":"https://flickr.com/photos/95271088@N05/22601219141","latitude":49.83832,"longitude":24.026304},{"url":"https://flickr.com/photos/95271088@N05/21969107453","title":"000027","photoUrl":"https://flickr.com/photos/95271088@N05/21969107453","latitude":49.8389,"longitude":24.028687},{"url":"https://flickr.com/photos/95271088@N05/21967526524","title":"000026","photoUrl":"https://flickr.com/photos/95271088@N05/21967526524","latitude":49.8389,"longitude":24.028687},{"url":"https://flickr.com/photos/95271088@N05/22402323070","title":"000025","photoUrl":"https://flickr.com/photos/95271088@N05/22402323070","latitude":49.842346,"longitude":24.034866},{"url":"https://flickr.com/photos/95271088@N05/21967518684","title":"000024","photoUrl":"https://flickr.com/photos/95271088@N05/21967518684","latitude":46.210945,"longitude":30.306097},{"url":"https://flickr.com/photos/95271088@N05/22402312210","title":"000022","photoUrl":"https://flickr.com/photos/95271088@N05/22402312210","latitude":46.21128,"longitude":30.307728},{"url":"https://flickr.com/photos/95271088@N05/21969085893","title":"000021","photoUrl":"https://flickr.com/photos/95271088@N05/21969085893","latitude":46.21128,"longitude":30.307728},{"url":"https://flickr.com/photos/95271088@N05/22564271976","title":"000020","photoUrl":"https://flickr.com/photos/95271088@N05/22564271976","latitude":46.21128,"longitude":30.307728},{"url":"https://flickr.com/photos/95271088@N05/22402304860","title":"000016","photoUrl":"https://flickr.com/photos/95271088@N05/22402304860","latitude":46.211,"longitude":30.306032},{"url":"https://flickr.com/photos/95271088@N05/22564266846","title":"000008","photoUrl":"https://flickr.com/photos/95271088@N05/22564266846","latitude":45.935074,"longitude":30.303274},{"url":"https://flickr.com/photos/95271088@N05/22601463371","title":"000001","photoUrl":"https://flickr.com/photos/95271088@N05/22601463371","latitude":46.194492,"longitude":30.343336},{"url":"https://flickr.com/photos/95271088@N05/22401997130","title":"91570011","photoUrl":"https://flickr.com/photos/95271088@N05/22401997130","latitude":49.835457,"longitude":24.010061},{"url":"https://flickr.com/photos/95271088@N05/22401993040","title":"91570003","photoUrl":"https://flickr.com/photos/95271088@N05/22401993040","latitude":48.97878,"longitude":23.471775},{"url":"https://flickr.com/photos/95271088@N05/22576404112","title":"91570002","photoUrl":"https://flickr.com/photos/95271088@N05/22576404112","latitude":48.97878,"longitude":23.471775},{"url":"https://flickr.com/photos/95271088@N05/22576401092","title":"91570001","photoUrl":"https://flickr.com/photos/95271088@N05/22576401092","latitude":48.97957,"longitude":23.47362},{"url":"https://flickr.com/photos/95271088@N05/22563941956","title":"student years","photoUrl":"https://flickr.com/photos/95271088@N05/22563941956","latitude":49.82608,"longitude":24.012316},{"url":"https://flickr.com/photos/95271088@N05/22590245655","title":"говорит москва","photoUrl":"https://flickr.com/photos/95271088@N05/22590245655","latitude":49.835365,"longitude":24.02167},{"url":"https://flickr.com/photos/95271088@N05/22590190115","title":"000003","photoUrl":"https://flickr.com/photos/95271088@N05/22590190115","latitude":49.83794,"longitude":24.031317},{"url":"https://flickr.com/photos/95271088@N05/22608532485","title":"39330015","photoUrl":"https://flickr.com/photos/95271088@N05/22608532485","latitude":49.828903,"longitude":24.041615},{"url":"https://flickr.com/photos/95271088@N05/22589880295","title":"39330017","photoUrl":"https://flickr.com/photos/95271088@N05/22589880295","latitude":49.828903,"longitude":24.041615},{"url":"https://flickr.com/photos/95271088@N05/22563861346","title":"39330008","photoUrl":"https://flickr.com/photos/95271088@N05/22563861346","latitude":49.827435,"longitude":24.063255},{"url":"https://flickr.com/photos/95271088@N05/21968872103","title":"Ivan Franko park","photoUrl":"https://flickr.com/photos/95271088@N05/21968872103","latitude":49.838356,"longitude":24.021189},{"url":"https://flickr.com/photos/95271088@N05/22564055316","title":"37590006","photoUrl":"https://flickr.com/photos/95271088@N05/22564055316","latitude":49.839005,"longitude":24.022207},{"url":"https://flickr.com/photos/95271088@N05/22563827396","title":"Katherine","photoUrl":"https://flickr.com/photos/95271088@N05/22563827396","latitude":49.820404,"longitude":24.039007},{"url":"https://flickr.com/photos/95271088@N05/21967063654","title":"30830011","photoUrl":"https://flickr.com/photos/95271088@N05/21967063654","latitude":49.820404,"longitude":24.039007},{"url":"https://flickr.com/photos/95271088@N05/22563818926","title":"30830013","photoUrl":"https://flickr.com/photos/95271088@N05/22563818926","latitude":49.820404,"longitude":24.039007},{"url":"https://flickr.com/photos/95271088@N05/22589819065","title":"30830015","photoUrl":"https://flickr.com/photos/95271088@N05/22589819065","latitude":49.820404,"longitude":24.039007},{"url":"https://flickr.com/photos/95271088@N05/22401847150","title":"30830016","photoUrl":"https://flickr.com/photos/95271088@N05/22401847150","latitude":49.820404,"longitude":24.039007},{"url":"https://flickr.com/photos/95271088@N05/22619681261","title":"30830019","photoUrl":"https://flickr.com/photos/95271088@N05/22619681261","latitude":49.820404,"longitude":24.039007},{"url":"https://flickr.com/photos/95271088@N05/21967047694","title":"30830021","photoUrl":"https://flickr.com/photos/95271088@N05/21967047694","latitude":49.820168,"longitude":24.040424},{"url":"https://flickr.com/photos/95271088@N05/22602092701","title":"87630025","photoUrl":"https://flickr.com/photos/95271088@N05/22602092701","latitude":46.20134,"longitude":30.35354},{"url":"https://flickr.com/photos/95271088@N05/21968124484","title":"87630026","photoUrl":"https://flickr.com/photos/95271088@N05/21968124484","latitude":46.20134,"longitude":30.35354},{"url":"https://flickr.com/photos/95271088@N05/21969697683","title":"87630031","photoUrl":"https://flickr.com/photos/95271088@N05/21969697683","latitude":49.826813,"longitude":24.030832}]